{
"v":"v1.1",
"m":"n",
"t":"20240409",
"FUNCTION_REFUSEMEDIAFOCUS":["enable","com.rd.tengfei.bdnotification"],
"FUNCTION_MULITIPLEPLAY":["enable","com.zhiliaoapp.musically.go"],
"FUNCTION_FADEOUTIN":["enable","com.whatsapp"],
"FUNCTION_MUTEAPPINPHONE":["enable","com.facebook.katana","com.ss.android.article.news","com.facebook.lite","com.snapchat.android","com.king.candycrushsaga","com.roblox.client","com.firsttouchgames.dls7","com.zhiliaoapp.musically","com.ss.android.ugc.trill","com.zhiliaoapp.musically.go","com.tencent.ig","com.ss.android.ugc.aweme"],
"FUNCTION_ADDPERFORMANCE":["enable","com.king.candycrushsaga"],
"FUNCTION_STOPPLAYBACK":["enable","com.facebook.katana","com.instagram.android","com.twitter.android"],
"FUNCTION_REQUEST_MAY_DUCK":["enable","com.tran.x"],
"FUNCTION_UPDATE_GAIN":["enable","com.tran.x"],
"FUNCTION_UPDATE_MAY_DUCK":["enable","com.tran.x"],
"FUNCTION_RECODER_FOCUS":["enable","com.ss.android.lark.transsion"],
"FUNCTION_ZERO_SOUND_DETECT":["enable","com.android.systemui","com.android.settings","com.transsion.magicshow","com.transsion.gamespace.app","com.transsion.fmradio","com.google.android.apps.youtube.music","com.afmobi.boomplayer"],
"FUNCTION_MEDIA_SMART_ENGINE_V1":["enable","com.zhiliaoapp.musically","com.ss.android.ugc.trill","com.transsion.magicshow","com.google.android.youtube"],
"FUNCTION_MEDIA_SMART_ENGINE_V2":["enable","com.ss.android.ugc.aweme","com.mxtech.videoplayer.ad","com.playit.videoplayer","com.kwai.bulldog","com.snaptube.premium","com.zhiliaoapp.musically","com.ss.android.ugc.trill","com.video.fun.app","com.transsion.magicshow","com.vkontakte.android","com.google.android.youtube"],
"FUNCTION_SET_WHATSAPP_PID":["enable","com.whatsapp","com.whatsapp.w4b","jp.naver.line.android"],
"FUNCTION_UPDATE_FLAGS_PRIMARY":["enable","com.zhiliao.musically.livewallpaper","com.tencent.qqlive"],
"FUNCTION_UPDATE_FLAGS_DEEP":["enable","com.miui.player"],
"FUNCTION_SET_ESPORT_PID":["enable","com.tencent.ig","com.dts.freefireth"],
"FUNCTION_SET_GVOICE_FLAG":["enable","com.transsion.smartpanel"],
"FUNCTION_NEED_CHANGE_VOIP":["enable","com.whatsapp","com.whatsapp.w4b"],
"FUNCTION_LVACFS_SYSTEM_CAMERA":["enable","com.transsion.camera","com.transsion.camera.debug"],
"FUNCTION_CHANGE_LEGENDS_NAME":["enable","com.mobile.legends:UnityKillsMe"],
"RESAMPLE_FIX_SUPPORT":["enable","com.tran.resample"]
}
